ultra_rest_client/__init__.py
ultra_rest_client/about.py
ultra_rest_client/connection.py
ultra_rest_client/ultra_rest_client.py
ultra_rest_client/utils/README.md
ultra_rest_client/utils/__init__.py
ultra_rest_client/utils/reports.py
ultra_rest_client/utils/tasks.py
ultra_rest_client-2.3.0.dist-info/METADATA
ultra_rest_client-2.3.0.dist-info/WHEEL
ultra_rest_client-2.3.0.dist-info/licenses/LICENSE
ultra_rest_client-2.3.0.dist-info/RECORD
