Metadata-Version: 2.3
Name: ultra-rest-client
Version: 2.3.0
Summary: A sample Python client for communicating with the UltraDNS REST API
Project-URL: Homepage, https://github.com/ultradns/python_rest_api_client
Author-email: ultradns <ultrassp-oss@vercara.com>
Keywords: ultra_rest_client
Classifier: Development Status :: 3 - Alpha
Classifier: License :: OSI Approved :: Apache Software License
Classifier: Topic :: Utilities
Requires-Dist: requests
